_hyctypes/__about__.py
_hyctypes/__init__.py
_hyctypes/C/__init__.py
_hyctypes/C/c_types.py
_hyctypes/C/dll.py
_hyctypes/C/enums.py
_hyctypes/C/function.py
_hyctypes/C/methods.py
_hyctypes/C/prototype.py
_hyctypes/C/basic_types/__init__.py
_hyctypes/C/basic_types/base.py
_hyctypes/C/basic_types/impls.py
_hyctypes/C/basic_types/type_hints.py
_hyctypes/C/basic_types/type_realities.py
_hyctypes/C/compound_types/__init__.py
_hyctypes/C/compound_types/base.py
_hyctypes/C/compound_types/impls.py
_hyctypes/C/compound_types/type_hints.py
_hyctypes/C/compound_types/type_realities.py
_hyctypes/C/py_types/__init__.py
_hyctypes/C/py_types/base.py
_hyctypes/C/py_types/type_realities.py
hydrogenlib_hyctypes-0.0.3.dist-info/METADATA
hydrogenlib_hyctypes-0.0.3.dist-info/WHEEL
hydrogenlib_hyctypes-0.0.3.dist-info/RECORD
