Metadata-Version: 2.4
Name: HydrogenLib-Hyctypes
Version: 0.0.3
Project-URL: Documentation, https://github.com/LittleSong2024/HydrogenLib#readme
Project-URL: Issues, https://github.com/LittleSong2024/HydrogenLib/issues
Project-URL: Source, https://github.com/LittleSong2024/HydrogenLib
Author-email: LittleSong2024 <LittleSong2024@outlook.com>
Classifier: Development Status :: 3 - Alpha
Classifier: Programming Language :: Python
Classifier: Programming Language :: Python :: 3.11
Classifier: Programming Language :: Python :: 3.12
Classifier: Programming Language :: Python :: 3.13
Classifier: Programming Language :: Python :: Implementation :: CPython
Classifier: Programming Language :: Python :: Implementation :: PyPy
Requires-Python: >=3.11
Requires-Dist: hydrogenlib-hycore
